leaflet_point/__init__.py
leaflet_point/admin.py
leaflet_point/tests.py
leaflet_point/static/leaflet_point/Control.Geocoder.css
leaflet_point/static/leaflet_point/Control.Geocoder.js
leaflet_point/static/leaflet_point/leaflet.css
leaflet_point/static/leaflet_point/leaflet.js
leaflet_point/static/leaflet_point/images/geocoder.png
leaflet_point/static/leaflet_point/images/layers-2x.png
leaflet_point/static/leaflet_point/images/layers.png
leaflet_point/static/leaflet_point/images/marker-icon-2x.png
leaflet_point/static/leaflet_point/images/marker-icon.png
leaflet_point/static/leaflet_point/images/marker-shadow.png
leaflet_point/templates/leaflet_point/admin/change_form.html
django_leaflet_point-0.3.1.dist-info/LICENSE
django_leaflet_point-0.3.1.dist-info/METADATA
django_leaflet_point-0.3.1.dist-info/WHEEL
django_leaflet_point-0.3.1.dist-info/top_level.txt
django_leaflet_point-0.3.1.dist-info/RECORD
